tagexpressions/__init__.py
tagexpressions/models.py
tagexpressions/parser.py
tag_expressions-2.0.1.dist-info/LICENSE
tag_expressions-2.0.1.dist-info/METADATA
tag_expressions-2.0.1.dist-info/WHEEL
tag_expressions-2.0.1.dist-info/top_level.txt
tag_expressions-2.0.1.dist-info/RECORD
